{
  "ad": "#b7cff9",
  "ae": "#c53334",
  "af": "#f5a081",
  "ag": "#f2cbb7",
  "ai": "#6b8df0",
  "al": "#6b8df0",
  "am": "#4b64d5",
  "ao": "#e0654f",
  "aq": "#f2cbb7",
  "ar": "#f7a98b",
  "as": "#4055c8",
  "at": "#be242e",
  "au": "#e7745b",
  "aw": "#80a3fa",
  "ax": "#7597f6",
  "az": "#7597f6",
  "ba": "#9fbfff",
  "bb": "#e3d9d3",
  "bd": "#cad8ef",
  "be": "#9bbcff",
  "bf": "#f3c8b2",
  "bg": "#6687ed",
  "bh": "#9bbcff",
  "bi": "#b5cdfa",
  "bj": "#d1dae9",
  "bl": "#f08a6c",
  "bm": "#7b9ff9",
  "bn": "#e0dbd8",
  "bo": "#f1cdba",
  "bq": "#485fd1",
  "br": "#f2c9b4",
  "bs": "#7093f3",
  "bt": "#4e68d8",
  "bv": "#c73635",
  "bw": "#c0282f",
  "by": "#ec8165",
  "bz": "#9fbfff",
  "ca": "#5977e3",
  "cc": "#f7b194",
  "cd": "#ccd9ed",
  "cf": "#6180e9",
  "cg": "#dbdcde",
  "ch": "#445acc",
  "ci": "#d44e41",
  "ck": "#90b2fe",
  "cl": "#f7b99e",
  "cm": "#a2c1ff",
  "cn": "#e2dad5",
  "co": "#e8d6cc",
  "cr": "#7699f6",
  "cu": "#be242e",
  "cv": "#f18f71",
  "cw": "#ca3b37",
  "cx": "#d75445",
  "cy": "#f2cbb7",
  "cz": "#d0473d",
  "de": "#5572df",
  "dj": "#7a9df8",
  "dk": "#485fd1",
  "dm": "#a7c5fe",
  "do": "#bcd2f7",
  "dz": "#94b6ff",
  "ec": "#e8765c",
  "ee": "#b2ccfb",
  "eg": "#97b8ff",
  "eh": "#e7d7ce",
  "er": "#6788ee",
  "es": "#ed8366",
  "et": "#516ddb",
  "fi": "#b8122a",
  "fj": "#f29072",
  "fm": "#7a9df8",
  "fo": "#3c4ec2",
  "fr": "#eb7d62",
  "ga": "#f7aa8c",
  "gb": "#f6a283",
  "gd": "#f29072",
  "ge": "#506bda",
  "gf": "#b2ccfb",
  "gg": "#5e7de7",
  "gh": "#e16751",
  "gi": "#f4c5ad",
  "gl": "#a9c6fd",
  "gm": "#4e68d8",
  "gn": "#a2c1ff",
  "gp": "#a7c5fe",
  "gq": "#f6a283",
  "gr": "#f5c0a7",
  "gt": "#d95847",
  "gu": "#d5dbe5",
  "gw": "#5f7fe8",
  "gy": "#f7a889",
  "hk": "#f39577",
  "hm": "#ebd3c6",
  "hn": "#f29072",
  "hr": "#dbdcde",
  "ht": "#e2dad5",
  "hu": "#c9d7f0",
  "id": "#4257c9",
  "ie": "#5b7ae5",
  "il": "#445acc",
  "im": "#f5c1a9",
  "in": "#a3c2fe",
  "io": "#dfdbd9",
  "iq": "#d44e41",
  "ir": "#8caffe",
  "is": "#c4d5f3",
  "it": "#f39778",
  "je": "#85a8fc",
  "jm": "#516ddb",
  "jo": "#9bbcff",
  "jp": "#6e90f2",
  "ke": "#cc403a",
  "kg": "#ec8165",
  "kh": "#f5c1a9",
  "ki": "#de614d",
  "km": "#ed8366",
  "kn": "#7699f6",
  "kp": "#d85646",
  "kr": "#e7d7ce",
  "kw": "#ec8165",
  "ky": "#d75445",
  "kz": "#a5c3fe",
  "la": "#5d7ce6",
  "lb": "#85a8fc",
  "lc": "#c9d7f0",
  "li": "#ea7b60",
  "lk": "#e16751",
  "lr": "#3c4ec2",
  "ls": "#dfdbd9",
  "lt": "#c5d6f2",
  "lu": "#82a6fb",
  "lv": "#5f7fe8",
  "ly": "#abc8fd",
  "ma": "#c83836",
  "mc": "#a6c4fe",
  "md": "#e1dad6",
  "me": "#f7ac8e",
  "mf": "#b5cdfa",
  "mg": "#be242e",
  "mh": "#c12b30",
  "mk": "#8db0fe",
  "ml": "#dcdddd",
  "mm": "#9fbfff",
  "mn": "#98b9ff",
  "mo": "#455cce",
  "mp": "#f3c8b2",
  "mq": "#dddcdc",
  "mr": "#4a63d3",
  "ms": "#97b8ff",
  "mt": "#d44e41",
  "mu": "#89acfd",
  "mv": "#688aef",
  "mw": "#dadce0",
  "mx": "#b8122a",
  "my": "#89acfd",
  "mz": "#f7b599",
  "na": "#f39577",
  "nc": "#88abfd",
  "ne": "#f6a283",
  "nf": "#b6cefa",
  "ng": "#f5c2aa",
  "ni": "#f5c1a9",
  "nl": "#e6d7cf",
  "no": "#5673e0",
  "np": "#e7745b",
  "nr": "#a6c4fe",
  "nu": "#7699f6",
  "nz": "#465ecf",
  "om": "#f1cdba",
  "pa": "#f7b497",
  "pe": "#3f53c6",
  "pf": "#e0dbd8",
  "pg": "#84a7fc",
  "ph": "#f6bea4",
  "pk": "#7295f4",
  "pl": "#f7b093",
  "pm": "#bcd2f7",
  "pn": "#cb3e38",
  "pr": "#6687ed",
  "pt": "#adc9fd",
  "pw": "#5e7de7",
  "py": "#cf453c",
  "qa": "#dd5f4b",
  "re": "#90b2fe",
  "ro": "#f7ba9f",
  "rs": "#ea7b60",
  "ru": "#ead4c8",
  "rw": "#e4d9d2",
  "sa": "#89acfd",
  "sb": "#5673e0",
  "sc": "#d75445",
  "sd": "#d65244",
  "se": "#f5c1a9",
  "sg": "#abc8fd",
  "sh": "#afcafc",
  "si": "#f6a385",
  "sj": "#d75445",
  "sk": "#d95847",
  "sl": "#f18d6f",
  "sm": "#f6bfa6",
  "sn": "#5470de",
  "so": "#6e90f2",
  "sr": "#d65244",
  "ss": "#f2c9b4",
  "st": "#3d50c3",
  "sv": "#5977e3",
  "sx": "#f7b99e",
  "sy": "#3c4ec2",
  "sz": "#6e90f2",
  "tc": "#e9d5cb",
  "td": "#f7af91",
  "tf": "#f6bda2",
  "tg": "#84a7fc",
  "th": "#f7a889",
  "tj": "#88abfd",
  "tk": "#a7c5fe",
  "tl": "#f49a7b",
  "tm": "#f6bda2",
  "tn": "#e36c55",
  "to": "#f7ba9f",
  "tr": "#edd2c3",
  "tt": "#5673e0",
  "tv": "#b6cefa",
  "tz": "#92b4fe",
  "ua": "#8badfd",
  "ug": "#bd1f2d",
  "um": "#bed2f6",
  "us": "#d85646",
  "uy": "#f5c2aa",
  "uz": "#ee8669",
  "va": "#dddcdc",
  "vc": "#eed0c0",
  "ve": "#dbdcde",
  "vg": "#799cf8",
  "vi": "#f6a586",
  "vn": "#97b8ff",
  "vu": "#4257c9",
  "wf": "#f6bea4",
  "ws": "#7396f5",
  "ye": "#ca3b37",
  "yt": "#c43032",
  "za": "#d1493f",
  "zm": "#b6cefa",
  "zw": "#3e51c5"
}